AUTHORS.rst
HISTORY.rst
LICENSE
MANIFEST.in
README.rst
setup.py
docs/Makefile
docs/authors.rst
docs/conf.py
docs/history.rst
docs/index.rst
docs/installation.rst
docs/make.bat
docs/modules.rst
docs/uhammer.rst
docs/usage.rst
docs/_build/html/_static/ajax-loader.gif
docs/_build/html/_static/comment-bright.png
docs/_build/html/_static/comment-close.png
docs/_build/html/_static/comment.png
docs/_build/html/_static/down-pressed.png
docs/_build/html/_static/down.png
docs/_build/html/_static/file.png
docs/_build/html/_static/minus.png
docs/_build/html/_static/plus.png
docs/_build/html/_static/up-pressed.png
docs/_build/html/_static/up.png
docs/_build/htmlcov/keybd_closed.png
docs/_build/htmlcov/keybd_open.png
tests/__init__.py
tests/conftest.py
tests/test_parallel.py
tests/test_persisting.py
tests/test_uhammer.py
tests/test_utils.py
tests/_regtest_outputs/test_parallel.test_check_and_fix_path.out
tests/_regtest_outputs/test_parallel.test_check_and_fix_path_fail.out
tests/_regtest_outputs/test_parallel.test_check_if_walkers_number_of_cores_fit.out
tests/_regtest_outputs/test_parallel.test_check_pool_1.out
tests/_regtest_outputs/test_parallel.test_check_pool_2.out
tests/_regtest_outputs/test_parallel.test_mpi_tasks.out
tests/_regtest_outputs/test_parallel.test_parallel_sampling.out
tests/_regtest_outputs/test_parallel.test_warning_for_oversubscription.out
tests/_regtest_outputs/test_persisting.test_restore_sampler__emcee_2.out
tests/_regtest_outputs/test_persisting.test_restore_sampler__emcee_3.out
tests/_regtest_outputs/test_uhammer.test_double_param.out
tests/_regtest_outputs/test_uhammer.test_empty_parameters.out
tests/_regtest_outputs/test_uhammer.test_invalid_prob_density.out
tests/_regtest_outputs/test_uhammer.test_line_fit__emcee_2.out
tests/_regtest_outputs/test_uhammer.test_line_fit__emcee_3.out
tests/_regtest_outputs/test_uhammer.test_param[0].out
tests/_regtest_outputs/test_uhammer.test_param[wrong_range1].out
uhammer.egg-info/PKG-INFO
uhammer.egg-info/SOURCES.txt
uhammer.egg-info/dependency_links.txt
uhammer.egg-info/not-zip-safe
uhammer.egg-info/requires.txt
uhammer.egg-info/top_level.txt