Metadata-Version: 1.1
Name: uhammer
Version: 0.4.0
Summary: Convenience layer for emcee sampler
Home-page: UNKNOWN
Author: Uwe Schmitt
Author-email: uwe.schmitt@id.ethz.ch
License: MIT license
Platform: UNKNOWN
Classifier: License :: OSI Approved :: MIT License
Classifier: Programming Language :: Python :: 2.7
Classifier: Programming Language :: Python :: 3
Classifier: Programming Language :: Python :: 3.4
Classifier: Programming Language :: Python :: 3.5
Classifier: Programming Language :: Python :: 3.6
Classifier: Programming Language :: Python :: 3.7
